Metadata-Version: 2.1
Name: nonebot-plugin-kindness-lesson
Version: 0.1.2
Summary: NoneBot 恩情课文生成插件 / Kindness Lesson Generating Plugin for NoneBot
Author-Email: zhaomaoniu <2667292003@qq.com>
License: MIT
Requires-Python: >=3.9
Requires-Dist: nonebot2>=2.4.0
Requires-Dist: openai>=1.54.4
